README.md
setup.cfg
setup.py
src/darjeeling/__init__.py
src/darjeeling/candidate.py
src/darjeeling/core.py
src/darjeeling/evaluator.py
src/darjeeling/exceptions.py
src/darjeeling/filters.py
src/darjeeling/localization.py
src/darjeeling/outcome.py
src/darjeeling/problem.py
src/darjeeling/settings.py
src/darjeeling/snippet.py
src/darjeeling/source.py
src/darjeeling/util.py
src/darjeeling/version.py
src/darjeeling.egg-info/PKG-INFO
src/darjeeling.egg-info/SOURCES.txt
src/darjeeling.egg-info/dependency_links.txt
src/darjeeling.egg-info/entry_points.txt
src/darjeeling.egg-info/requires.txt
src/darjeeling.egg-info/top_level.txt
src/darjeeling/cli/__init__.py
src/darjeeling/searcher/__init__.py
src/darjeeling/searcher/base.py
src/darjeeling/searcher/exhaustive.py
src/darjeeling/searcher/genetic.py
src/darjeeling/transformation/__init__.py
src/darjeeling/transformation/base.py
src/darjeeling/transformation/classic.py
src/darjeeling/transformation/line.py
src/darjeeling/transformation/rooibos.py